kagtcprlib/__init__.py
kagtcprlib/client.py
kagtcprlib/constants.py
kagtcprlib/exceptions.py
kagtcprlib/handlers.py
kagtcprlib/utils.py
kagtcprlib/webinterface.py
kagtcprlib/opt/__init__.py
kagtcprlib/opt/kagladder/__init__.py
kagtcprlib/opt/kagladder/xmlrequesthandler.py
kagtcprlib/web/__init__.py
kagtcprlib/web/index.html
kagtcprlib/web/main.js
kagtcprlib/web/stylesheet.css
kagtcprlib/web/lib/jquery/jquery.min.js
kagtcprlib/web/lib/materialize/LICENSE
kagtcprlib/web/lib/materialize/README.md
kagtcprlib/web/lib/materialize/css/materialize.css
kagtcprlib/web/lib/materialize/css/materialize.min.css
kagtcprlib/web/lib/materialize/js/materialize.js
kagtcprlib/web/lib/materialize/js/materialize.min.js
kagtcprlib/web/lib/vue/vue.min.js
kagtcprlib-0.2.1.dist-info/LICENSE.md
kagtcprlib-0.2.1.dist-info/METADATA
kagtcprlib-0.2.1.dist-info/WHEEL
kagtcprlib-0.2.1.dist-info/top_level.txt
kagtcprlib-0.2.1.dist-info/RECORD
