Metadata-Version: 2.1
Name: kagtcprlib
Version: 0.2.1
Summary: TCPR library for King Arthur's Gold
Home-page: https://github.com/benjamingorman/kagtcprlib
Author: Benjamin Gorman
Author-email: 8076bgorman@gmail.com
License: UNKNOWN
Platform: UNKNOWN
Classifier: Programming Language :: Python
Classifier: Programming Language :: Python :: 3
Classifier: Operating System :: OS Independent
License-File: LICENSE.md
Requires-Dist: toml
Requires-Dist: xmltodict
Requires-Dist: simple-websocket-server
